LICENSE
MANIFEST.in
README.md
setup.py
docums_img2fig_plugin.egg-info/PKG-INFO
docums_img2fig_plugin.egg-info/SOURCES.txt
docums_img2fig_plugin.egg-info/dependency_links.txt
docums_img2fig_plugin.egg-info/entry_points.txt
docums_img2fig_plugin.egg-info/requires.txt
docums_img2fig_plugin.egg-info/top_level.txt
src/__init__.py
src/plugin.py