Metadata-Version: 2.1
Name: docums-img2fig-plugin
Version: 0.9.3
Summary: A Docums plugin that converts markdown encoded images into <figure> elements.
Home-page: https://github.com/khanhduy1407/docums-img2fig-plugin
Author: NKDuy
Author-email: kn145660@gmail.com
License: MIT
Keywords: docums python markdown
Platform: UNKNOWN
Requires-Python: >=3.5
